opentechcalendartools/__init__.py
opentechcalendartools/__main__.py
opentechcalendartools/cli.py
opentechcalendartools/worker.py
opentechcalendartools-0.1.0.dist-info/licenses/LICENSE
opentechcalendartools-0.1.0.dist-info/METADATA
opentechcalendartools-0.1.0.dist-info/WHEEL
opentechcalendartools-0.1.0.dist-info/top_level.txt
opentechcalendartools-0.1.0.dist-info/RECORD
