Metadata-Version: 2.4
Name: opentechcalendartools
Version: 0.1.0
Home-page: https://github.com/TeacakeTech/opentechcalendar-tools
Author: Teacake Tech
Author-email: hello@teacaketech.scot
Project-URL: Home Page, https://opentechcalendar.co.uk/
Project-URL: Issues, https://github.com/TeacakeTech/opentechcalendar-tools/issues
Project-URL: Source, https://github.com/TeacakeTech/opentechcalendar-tools
Requires-Python: >=3.12
License-File: LICENSE
Requires-Dist: datatig
Requires-Dist: requests
Requires-Dist: icalendar
Requires-Dist: pyyaml
Provides-Extra: dev
Requires-Dist: black; extra == "dev"
Requires-Dist: isort; extra == "dev"
Requires-Dist: flake8; extra == "dev"
Requires-Dist: mypy; extra == "dev"
Dynamic: author
Dynamic: author-email
Dynamic: home-page
Dynamic: license-file
Dynamic: project-url
Dynamic: provides-extra
Dynamic: requires-dist
Dynamic: requires-python
